arrm/MoBL_ARMS_module2_4_onemuscle_afferent.osim
arrm/MoBL_ARMS_module2_4_onemuscle_afferent_no_string.osim
arrm/SimTKcommon.dll
arrm/SimTKmath.dll
arrm/SimTKsimbody.dll
arrm/_arrm.pyd
arrm/adolc.dll
arrm/arrm.py
arrm/casadi.dll
arrm/casadi_conic_nlpsol.dll
arrm/casadi_conic_qrqp.dll
arrm/casadi_importer_shell.dll
arrm/casadi_integrator_collocation.dll
arrm/casadi_integrator_cvodes.dll
arrm/casadi_integrator_idas.dll
arrm/casadi_integrator_rk.dll
arrm/casadi_interpolant_bspline.dll
arrm/casadi_interpolant_linear.dll
arrm/casadi_linsol_csparse.dll
arrm/casadi_linsol_csparsecholesky.dll
arrm/casadi_linsol_ldl.dll
arrm/casadi_linsol_lsqr.dll
arrm/casadi_linsol_qr.dll
arrm/casadi_linsol_symbolicqr.dll
arrm/casadi_linsol_tridiag.dll
arrm/casadi_nlpsol_ipopt.dll
arrm/casadi_nlpsol_qrsqp.dll
arrm/casadi_nlpsol_scpgen.dll
arrm/casadi_nlpsol_sqpmethod.dll
arrm/casadi_rootfinder_fast_newton.dll
arrm/casadi_rootfinder_kinsol.dll
arrm/casadi_rootfinder_newton.dll
arrm/casadi_rootfinder_nlpsol.dll
arrm/casadi_sundials_common.dll
arrm/casadi_xmlfile_tinyxml.dll
arrm/concrt140.dll
arrm/flang.dll
arrm/flangrti.dll
arrm/glut32.dll
arrm/libblas.dll
arrm/libgcc_s_sjlj-1.dll
arrm/libgfortran-3.dll
arrm/liblapack.dll
arrm/libomp.dll
arrm/libquadmath-0.dll
arrm/msvcp140.dll
arrm/msvcp140_1.dll
arrm/msvcp140_2.dll
arrm/msvcp140_codecvt_ids.dll
arrm/openblas.dll
arrm/osimActuators.dll
arrm/osimAnalyses.dll
arrm/osimCommon.dll
arrm/osimExampleComponents.dll
arrm/osimLepton.dll
arrm/osimMoco.dll
arrm/osimSimulation.dll
arrm/osimTools.dll
arrm/simbody-visualizer.exe
arrm/tropter.dll
arrm/vcruntime140.dll
arrm/vcruntime140_1.dll
arrm/Geometry/1mc.vtp
arrm/Geometry/2distph.vtp
arrm/Geometry/2mc.vtp
arrm/Geometry/2midph.vtp
arrm/Geometry/2proxph.vtp
arrm/Geometry/3distph.vtp
arrm/Geometry/3mc.vtp
arrm/Geometry/3midph.vtp
arrm/Geometry/3proxph.vtp
arrm/Geometry/4distph.vtp
arrm/Geometry/4mc.vtp
arrm/Geometry/4midph.vtp
arrm/Geometry/4proxph.vtp
arrm/Geometry/5distph.vtp
arrm/Geometry/5mc.vtp
arrm-0.0.12.dist-info/METADATA
arrm-0.0.12.dist-info/WHEEL
arrm-0.0.12.dist-info/top_level.txt
arrm-0.0.12.dist-info/RECORD
